wcglib/__init__.py
wcglib/__version__.py
wcglib/log_utils.py
wcglib/wcg.py
wcglib-0.1.0.dist-info/LICENSE
wcglib-0.1.0.dist-info/METADATA
wcglib-0.1.0.dist-info/WHEEL
wcglib-0.1.0.dist-info/top_level.txt
wcglib-0.1.0.dist-info/RECORD
