Metadata-Version: 2.1
Name: wcglib
Version: 0.1.0
Summary: Keep It Simple, Stupid
Home-page: https://github.com/wcg-data/wcglib.git
Author: Vidor Joyce
Author-email: vdr573045093@hotmail.com
License: MIT
Platform: UNKNOWN
Classifier: License :: OSI Approved :: MIT License
Classifier: Programming Language :: Python
Classifier: Programming Language :: Python :: 3
Classifier: Programming Language :: Python :: 3.7
Classifier: Programming Language :: Python :: 3.8
Classifier: Programming Language :: Python :: 3.9
Classifier: Programming Language :: Python :: 3.10
Requires-Python: >=3.7.0
License-File: LICENSE
